[{
        "Achternaam": "Puffelen van",
        "Voornaam": "Piet",
        "E-mailadres": "onbekend@test.nl",
        "Rol":"Administrator",
        "Permissies": "<a href='#'><i class='icon-arrow-right'></i></a>",
        "Actions": "<a href='#' (click)='open(content,$event)' false><i class='icon-note font-medium-1 mr-2'></i></a><a href='#' (deleteConfirm)='onDeleteConfirm($event)'><i class='icon-trash font-medium-1 mr-2'></i></a>"
    },
    {
        "Achternaam": "Puffelen van",
        "Voornaam": "Piet",
        "E-mailadres": "onbekend@test.nl",
        "Rol":"Inspecteur",
        "Permissies": "<a href='#'><i class='icon-arrow-right'></i></a>",
        "Actions": "<a href='#' (click)='open(content,$event)' false><i class='icon-note font-medium-1 mr-2'></i></a><a href='#' (deleteConfirm)='onDeleteConfirm($event)'><i class='icon-trash font-medium-1 mr-2'></i></a>"
    },
    {
        "Achternaam": "Puffelen van",
        "Voornaam": "Piet",
        "E-mailadres": "onbekend@test.nl",
        "Rol":"Administratief",
        "Permissies": "<a href='#'><i class='icon-arrow-right'></i></a>",
        "Actions": "<a href='#' (click)='open(content,$event)' false><i class='icon-note font-medium-1 mr-2'></i></a><a href='#' (deleteConfirm)='onDeleteConfirm($event)'><i class='icon-trash font-medium-1 mr-2'></i></a>"
    },
    {
        "Achternaam": "Puffelen van",
        "Voornaam": "Piet",
        "E-mailadres": "onbekend@test.nl",
        "Rol":"Administrator",
        "Permissies": "<a href='#'><i class='icon-arrow-right'></i></a>",
        "Actions": "<a href='#' (click)='open(content,$event)' false><i class='icon-note font-medium-1 mr-2'></i></a><a href='#' (deleteConfirm)='onDeleteConfirm($event)'><i class='icon-trash font-medium-1 mr-2'></i></a>"
    },
    {
        "Achternaam": "Puffelen van",
        "Voornaam": "Piet",
        "E-mailadres": "onbekend@test.nl",
        "Rol":"Inspecteur",
        "Permissies": "<a href='#'><i class='icon-arrow-right'></i></a>",
        "Actions": "<a href='#' (click)='open(content,$event)' false><i class='icon-note font-medium-1 mr-2'></i></a><a href='#' (deleteConfirm)='onDeleteConfirm($event)'><i class='icon-trash font-medium-1 mr-2'></i></a>"
    },
    {
        "Achternaam": "Puffelen van",
        "Voornaam": "Piet",
        "E-mailadres": "onbekend@test.nl",
        "Rol":"Administratief",
        "Permissies": "<a href='#'><i class='icon-arrow-right'></i></a>",
        "Actions": "<a href='#' (click)='open(content,$event)' false><i class='icon-note font-medium-1 mr-2'></i></a><a href='#' (deleteConfirm)='onDeleteConfirm($event)'><i class='icon-trash font-medium-1 mr-2'></i></a>"
    }
]